pytest_bravado.py
pytest_bravado-1.0.10.dist-info/entry_points.txt
pytest_bravado-1.0.10.dist-info/WHEEL
pytest_bravado-1.0.10.dist-info/METADATA
pytest_bravado-1.0.10.dist-info/RECORD
